LICENSE.txt
MANIFEST.in
README.rst
bootstrap-buildout.py
buildout.cfg
fixed_perturbation.py
random_perturbation.py
setup.py
version.txt
xfacereclib.paper.IET2015.egg-info/PKG-INFO
xfacereclib.paper.IET2015.egg-info/SOURCES.txt
xfacereclib.paper.IET2015.egg-info/dependency_links.txt
xfacereclib.paper.IET2015.egg-info/entry_points.txt
xfacereclib.paper.IET2015.egg-info/namespace_packages.txt
xfacereclib.paper.IET2015.egg-info/requires.txt
xfacereclib.paper.IET2015.egg-info/top_level.txt
xfacereclib/paper/__init__.py
xfacereclib/paper/IET2015/__init__.py
xfacereclib/paper/IET2015/configuration/__init__.py
xfacereclib/paper/IET2015/configuration/database.py
xfacereclib/paper/IET2015/configuration/grid.py
xfacereclib/paper/IET2015/facereclib/FixedPerturbation.py
xfacereclib/paper/IET2015/facereclib/RandomPerturbation.py
xfacereclib/paper/IET2015/facereclib/ToolChain.py
xfacereclib/paper/IET2015/facereclib/__init__.py
xfacereclib/paper/IET2015/script/__init__.py
xfacereclib/paper/IET2015/script/annotation_types.py
xfacereclib/paper/IET2015/script/faceverify.py
xfacereclib/paper/IET2015/script/plot_results.py
xfacereclib/paper/IET2015/script/unpack_annotations.py