Metadata-Version: 1.1
Name: xfacereclib.paper.IET2015
Version: 1.0.1
Summary: Source code to reproduce the paper "Impact of Eye Detection Error on Face Recognition Performance"
Home-page: http://github.com/bioidiap/xfacereclib.paper.IET2015
Author: Manuel Guenther
Author-email: manuel.guenther@idiap.ch
License: GPLv3
Keywords: face recognition,eye detection,geometric normalization,facereclib
Platform: UNKNOWN
Classifier: Framework :: Bob
Classifier: Development Status :: 4 - Beta
Classifier: Intended Audience :: Developers
Classifier: License :: OSI Approved :: GNU General Public License v3 (GPLv3)
Classifier: Natural Language :: English
Classifier: Programming Language :: Python
Classifier: Topic :: Scientific/Engineering :: Artificial Intelligence
